LICENSE.rst
MANIFEST.in
README.rst
setup.py
ur_cb2/__init__.py
ur_cb2/cb2_move_to_points.py
ur_cb2/cb2_robot.py
ur_cb2/cb2_robot_example.py
ur_cb2.egg-info/PKG-INFO
ur_cb2.egg-info/SOURCES.txt
ur_cb2.egg-info/dependency_links.txt
ur_cb2.egg-info/entry_points.txt
ur_cb2.egg-info/not-zip-safe
ur_cb2.egg-info/top_level.txt
ur_cb2/receive/__init__.py
ur_cb2/receive/cb2_receive.py
ur_cb2/receive/cb2_receive_example.py
ur_cb2/receive/cb2_store_points.py
ur_cb2/send/__init__.py
ur_cb2/send/cb2_send.py
ur_cb2/send/cb2_send_example.py