Metadata-Version: 1.1
Name: ur-cb2
Version: 0.1
Summary: A package to interface with a UR CB2 Robot over TCP/IP
Home-page: https://github.com/IRIM-Technology-Transition-Lab/ur_cb2.git
Author: Michael Sobrepera
Author-email: mjsobrep@live.com
License: The MIT License (MIT)
